{"objectIdFieldName":"OBJECTID","uniqueIdField":{"name":"OBJECTID","isSystemMaintained":true},"globalIdFieldName":"","hasZ":false,"hasM":false,"spatialReference":{"wkid":102100,"latestWkid":3857},"fields":[{"name":"OBJECTID","type":"esriFieldTypeOID","alias":"OBJECTID","sqlType":"sqlTypeInteger","domain":null,"defaultValue":null},{"name":"count","type":"esriFieldTypeInteger","alias":"count","sqlType":"sqlTypeOther","domain":null,"defaultValue":null},{"name":"NRBeamFailureEvt","type":"esriFieldTypeString","alias":"NRBeamFailureEvt","sqlType":"sqlTypeOther","domain":null,"defaultValue":null,"length":128},{"name":"NRRlfCband","type":"esriFieldTypeString","alias":"NRRlfCband","sqlType":"sqlTypeOther","domain":null,"defaultValue":null,"length":128},{"name":"LTERrcConRej","type":"esriFieldTypeString","alias":"LTERrcConRej","sqlType":"sqlTypeOther","domain":null,"defaultValue":null,"length":128},{"name":"LTEReselToGsmUmtsFail","type":"esriFieldTypeString","alias":"LTEReselToGsmUmtsFail","sqlType":"sqlTypeOther","domain":null,"defaultValue":null,"length":128},{"name":"lteRrcConSetupFailure","type":"esriFieldTypeString","alias":"lteRrcConSetupFailure","sqlType":"sqlTypeOther","domain":null,"defaultValue":null,"length":128},{"name":"NrSetupFailureNW","type":"esriFieldTypeString","alias":"NrSetupFailureNW","sqlType":"sqlTypeOther","domain":null,"defaultValue":null,"length":128},{"name":"LTEAttRej","type":"esriFieldTypeString","alias":"LTEAttRej","sqlType":"sqlTypeOther","domain":null,"defaultValue":null,"length":128},{"name":"NrSetupSuccessCband","type":"esriFieldTypeString","alias":"NrSetupSuccessCband","sqlType":"sqlTypeOther","domain":null,"defaultValue":null,"length":128},{"name":"NRRlfNW","type":"esriFieldTypeString","alias":"NRRlfNW","sqlType":"sqlTypeOther","domain":null,"defaultValue":null,"length":128},{"name":"VoLTECallEndEvt","type":"esriFieldTypeString","alias":"VoLTECallEndEvt","sqlType":"sqlTypeOther","domain":null,"defaultValue":null,"length":128},{"name":"LTERlf","type":"esriFieldTypeString","alias":"LTERlf","sqlType":"sqlTypeOther","domain":null,"defaultValue":null,"length":128},{"name":"LTEPdnRej","type":"esriFieldTypeString","alias":"LTEPdnRej","sqlType":"sqlTypeOther","domain":null,"defaultValue":null,"length":128},{"name":"NRRachSuccessEvt","type":"esriFieldTypeString","alias":"NRRachSuccessEvt","sqlType":"sqlTypeOther","domain":null,"defaultValue":null,"length":128},{"name":"LTECallInefAtmpt","type":"esriFieldTypeString","alias":"LTECallInefAtmpt","sqlType":"sqlTypeOther","domain":null,"defaultValue":null,"length":128},{"name":"lteTaReqCnt","type":"esriFieldTypeString","alias":"lteTaReqCnt","sqlType":"sqlTypeOther","domain":null,"defaultValue":null,"length":128},{"name":"LTEMobilityFromEutraFail","type":"esriFieldTypeString","alias":"LTEMobilityFromEutraFail","sqlType":"sqlTypeOther","domain":null,"defaultValue":null,"length":128},{"name":"NRBeamSwitchEvt","type":"esriFieldTypeString","alias":"NRBeamSwitchEvt","sqlType":"sqlTypeOther","domain":null,"defaultValue":null,"length":128},{"name":"ltePdnConntReqCnt","type":"esriFieldTypeString","alias":"ltePdnConntReqCnt","sqlType":"sqlTypeOther","domain":null,"defaultValue":null,"length":128},{"name":"lteRrcConReqCnt","type":"esriFieldTypeString","alias":"lteRrcConReqCnt","sqlType":"sqlTypeOther","domain":null,"defaultValue":null,"length":128},{"name":"lteSrvReqCnt","type":"esriFieldTypeString","alias":"lteSrvReqCnt","sqlType":"sqlTypeOther","domain":null,"defaultValue":null,"length":128},{"name":"NrReleaseEvt","type":"esriFieldTypeString","alias":"NrReleaseEvt","sqlType":"sqlTypeOther","domain":null,"defaultValue":null,"length":128},{"name":"NrSetupFailureCband","type":"esriFieldTypeString","alias":"NrSetupFailureCband","sqlType":"sqlTypeOther","domain":null,"defaultValue":null,"length":128},{"name":"NRScgFailureEvt","type":"esriFieldTypeString","alias":"NRScgFailureEvt","sqlType":"sqlTypeOther","domain":null,"defaultValue":null,"length":128},{"name":"NRRrcNewCellIndEvt","type":"esriFieldTypeString","alias":"NRRrcNewCellIndEvt","sqlType":"sqlTypeOther","domain":null,"defaultValue":null,"length":128},{"name":"NRBeamFailureEvtNW","type":"esriFieldTypeString","alias":"NRBeamFailureEvtNW","sqlType":"sqlTypeOther","domain":null,"defaultValue":null,"length":128},{"name":"LTEVoLTEAbort","type":"esriFieldTypeString","alias":"LTEVoLTEAbort","sqlType":"sqlTypeOther","domain":null,"defaultValue":null,"length":128},{"name":"NRRrcHoFailEvt","type":"esriFieldTypeString","alias":"NRRrcHoFailEvt","sqlType":"sqlTypeOther","domain":null,"defaultValue":null,"length":128},{"name":"LTEIntraHoFail","type":"esriFieldTypeString","alias":"LTEIntraHoFail","sqlType":"sqlTypeOther","domain":null,"defaultValue":null,"length":128},{"name":"lteRrcConSetupCmpCnt","type":"esriFieldTypeString","alias":"lteRrcConSetupCmpCnt","sqlType":"sqlTypeOther","domain":null,"defaultValue":null,"length":128},{"name":"LTEIntraReselFail","type":"esriFieldTypeString","alias":"LTEIntraReselFail","sqlType":"sqlTypeOther","domain":null,"defaultValue":null,"length":128},{"name":"LTETaRej","type":"esriFieldTypeString","alias":"LTETaRej","sqlType":"sqlTypeOther","domain":null,"defaultValue":null,"length":128},{"name":"lteHoCmdCnt","type":"esriFieldTypeString","alias":"lteHoCmdCnt","sqlType":"sqlTypeOther","domain":null,"defaultValue":null,"length":128},{"name":"VoLTECallStartEvt","type":"esriFieldTypeString","alias":"VoLTECallStartEvt","sqlType":"sqlTypeOther","domain":null,"defaultValue":null,"length":128},{"name":"LTERrcConRestRej","type":"esriFieldTypeString","alias":"LTERrcConRestRej","sqlType":"sqlTypeOther","domain":null,"defaultValue":null,"length":128},{"name":"LTEVoLTEDrop","type":"esriFieldTypeString","alias":"LTEVoLTEDrop","sqlType":"sqlTypeOther","domain":null,"defaultValue":null,"length":128},{"name":"LTEOos","type":"esriFieldTypeString","alias":"LTEOos","sqlType":"sqlTypeOther","domain":null,"defaultValue":null,"length":128},{"name":"LTEServiceRej","type":"esriFieldTypeString","alias":"LTEServiceRej","sqlType":"sqlTypeOther","domain":null,"defaultValue":null,"length":128},{"name":"NRRachAbortEvt","type":"esriFieldTypeString","alias":"NRRachAbortEvt","sqlType":"sqlTypeOther","domain":null,"defaultValue":null,"length":128},{"name":"LTESibReadFailure","type":"esriFieldTypeString","alias":"LTESibReadFailure","sqlType":"sqlTypeOther","domain":null,"defaultValue":null,"length":128},{"name":"NRRachFailureEvt","type":"esriFieldTypeString","alias":"NRRachFailureEvt","sqlType":"sqlTypeOther","domain":null,"defaultValue":null,"length":128},{"name":"LTEReselFromGsmUmtsFail","type":"esriFieldTypeString","alias":"LTEReselFromGsmUmtsFail","sqlType":"sqlTypeOther","domain":null,"defaultValue":null,"length":128},{"name":"LTEAuthRej","type":"esriFieldTypeString","alias":"LTEAuthRej","sqlType":"sqlTypeOther","domain":null,"defaultValue":null,"length":128},{"name":"nrScgCfgEvt","type":"esriFieldTypeString","alias":"nrScgCfgEvt","sqlType":"sqlTypeOther","domain":null,"defaultValue":null,"length":128},{"name":"NrSetupSuccess","type":"esriFieldTypeString","alias":"NrSetupSuccess","sqlType":"sqlTypeOther","domain":null,"defaultValue":null,"length":128},{"name":"NRBeamRecoveryFailureEvt","type":"esriFieldTypeString","alias":"NRBeamRecoveryFailureEvt","sqlType":"sqlTypeOther","domain":null,"defaultValue":null,"length":128},{"name":"lteAttReqCnt","type":"esriFieldTypeString","alias":"lteAttReqCnt","sqlType":"sqlTypeOther","domain":null,"defaultValue":null,"length":128},{"name":"NRRlf","type":"esriFieldTypeString","alias":"NRRlf","sqlType":"sqlTypeOther","domain":null,"defaultValue":null,"length":128},{"name":"NRBeamFailureEvtCband","type":"esriFieldTypeString","alias":"NRBeamFailureEvtCband","sqlType":"sqlTypeOther","domain":null,"defaultValue":null,"length":128}],"features":[{"attributes":{"count":169,"NRRrcNewCellIndEvt":"1","OBJECTID":1106614590},"geometry":{"x":-8251499.372260304,"y":4999000.000000002}},{"attributes":{"count":109,"NRRachFailureEvt":"1","OBJECTID":964707155},"geometry":{"x":-8254963.473875443,"y":4975000}},{"attributes":{"count":71,"NRRachFailureEvt":"1","OBJECTID":2051869960},"geometry":{"x":-8220322.457724066,"y":4992999.999999997}},{"attributes":{"count":74,"NRRrcNewCellIndEvt":"1","OBJECTID":1996561480},"geometry":{"x":-8253231.423067873,"y":4995999.999999997}},{"attributes":{"count":14,"NRRachFailureEvt":"1","OBJECTID":1994127546},"geometry":{"x":-8308657.048910078,"y":4960000.000000002}},{"attributes":{"count":20,"LTESibReadFailure":"1","OBJECTID":110664078},"geometry":{"x":-8308657.048910078,"y":4912000.000000001}},{"attributes":{"count":12,"LTERlf":"1","OBJECTID":419732768},"geometry":{"x":-8246303.2198376,"y":5001999.999999998}},{"attributes":{"count":18,"LTEOos":"1","OBJECTID":208091456},"geometry":{"x":-8306924.998102508,"y":4950999.999999998}},{"attributes":{"count":3,"LTEPdnRej":"1","OBJECTID":2122226271},"geometry":{"x":-8296532.693257095,"y":4962999.999999999}},{"attributes":{"count":7,"NRBeamFailureEvt":"1","OBJECTID":621615829},"geometry":{"x":-8298264.744064665,"y":4971999.999999999}},{"attributes":{"count":8,"NrSetupFailure":"1","OBJECTID":1761762768},"geometry":{"x":-8249767.321452735,"y":4995999.999999997}},{"attributes":{"count":5,"LTERlf":"1","OBJECTID":941960290},"geometry":{"x":-8242839.11822246,"y":5001999.999999998}},{"attributes":{"count":3,"LTESibReadFailure":"1","OBJECTID":653169261},"geometry":{"x":-8246303.2198376,"y":4971999.999999999}},{"attributes":{"count":5,"LTEIntraReselFail":"1","OBJECTID":1765770440},"geometry":{"x":-8303460.89648737,"y":4950999.999999998}},{"attributes":{"count":4,"NRRachFailureEvt":"1","OBJECTID":967484139},"geometry":{"x":-8256695.524683014,"y":4983999.999999998}},{"attributes":{"count":3,"lteRrcConSetupFailure":"1","OBJECTID":379016930},"geometry":{"x":-8248035.270645166,"y":5011000}},{"attributes":{"count":4,"NRRachFailureEvt":"1","OBJECTID":230131186},"geometry":{"x":-8256695.524683014,"y":4971999.999999999}},{"attributes":{"count":3,"LTERlf":"1","OBJECTID":1681723331},"geometry":{"x":-8254963.473875443,"y":4981000.000000001}},{"attributes":{"count":3,"NRRachFailureEvt":"1","OBJECTID":1882454979},"geometry":{"x":-8223786.559339202,"y":4986999.999999998}},{"attributes":{"count":3,"NRRachFailureEvt":"1","OBJECTID":243841036},"geometry":{"x":-8220322.457724066,"y":4986999.999999998}},{"attributes":{"count":3,"lteRrcConReqCnt":"1","OBJECTID":1890010867},"geometry":{"x":-8241107.067414891,"y":5004999.999999996}},{"attributes":{"count":3,"NRRachFailureEvt":"1","OBJECTID":1741556995},"geometry":{"x":-8246303.2198376,"y":4906000}},{"attributes":{"count":1,"LTERlf":"1","OBJECTID":1398378412},"geometry":{"x":-8242839.11822246,"y":4971999.999999999}},{"attributes":{"count":3,"NRRachAbortEvt":"1","OBJECTID":1448131289},"geometry":{"x":-8218590.406916495,"y":4989999.999999999}},{"attributes":{"count":2,"NRRachFailureEvt":"1","OBJECTID":1435160616},"geometry":{"x":-8258427.575490579,"y":4872999.999999996}},{"attributes":{"count":1,"LTERlf":"1","OBJECTID":558371990},"geometry":{"x":-8256695.524683014,"y":4923999.999999999}},{"attributes":{"count":2,"lteRrcConSetupFailure":"1","OBJECTID":641779565},"geometry":{"x":-8287872.439219251,"y":4947999.999999997}},{"attributes":{"count":2,"lteRrcConSetupFailure":"1","OBJECTID":1610985362},"geometry":{"x":-8216858.356108926,"y":4968999.999999996}},{"attributes":{"count":2,"LTEIntraReselFail":"1","OBJECTID":2489127},"geometry":{"x":-8206466.051263513,"y":4968999.999999996}},{"attributes":{"count":2,"lteRrcConSetupFailure":"1","OBJECTID":1288468159},"geometry":{"x":-8204734.000455943,"y":4971999.999999999}},{"attributes":{"count":2,"LTERlf":"1","OBJECTID":735830526},"geometry":{"x":-8261891.677105717,"y":4981000.000000001}},{"attributes":{"count":2,"NRRrcNewCellIndEvt":"1","OBJECTID":1706455956},"geometry":{"x":-8258427.575490579,"y":4981000.000000001}},{"attributes":{"count":1,"lteRrcConSetupCmpCnt":"1","OBJECTID":341498472},"geometry":{"x":-8258427.575490579,"y":4992999.999999997}},{"attributes":{"count":1,"lteRrcConSetupFailure":"1","OBJECTID":922637142},"geometry":{"x":-8244571.169030029,"y":4999000.000000002}},{"attributes":{"count":2,"NRRrcNewCellIndEvt":"1","OBJECTID":856848177},"geometry":{"x":-8244571.169030029,"y":5004999.999999996}},{"attributes":{"count":1,"NRRrcNewCellIndEvt":"1","OBJECTID":1182469116},"geometry":{"x":-8258427.575490579,"y":4866999.999999999}},{"attributes":{"count":1,"NRRrcNewCellIndEvt":"1","OBJECTID":842542796},"geometry":{"x":-8253231.423067873,"y":4881999.999999998}},{"attributes":{"count":1,"LTEIntraReselFail":"1","OBJECTID":2125578276},"geometry":{"x":-8303460.89648737,"y":4908999.999999998}},{"attributes":{"count":1,"LTEOos":"1","OBJECTID":1009948441},"geometry":{"x":-8270551.931143562,"y":4923999.999999999}},{"attributes":{"count":1,"NRRachFailureEvt":"1","OBJECTID":749341514},"geometry":{"x":-8260159.626298148,"y":4923999.999999999}},{"attributes":{"count":1,"NRRrcNewCellIndEvt":"1","OBJECTID":562151826},"geometry":{"x":-8263623.7279132875,"y":4930000}},{"attributes":{"count":1,"NRRrcNewCellIndEvt":"1","OBJECTID":1529138530},"geometry":{"x":-8270551.931143562,"y":4935999.999999997}},{"attributes":{"count":1,"NRRrcNewCellIndEvt":"1","OBJECTID":798761960},"geometry":{"x":-8272283.98195113,"y":4950999.999999998}},{"attributes":{"count":1,"NRRrcNewCellIndEvt":"1","OBJECTID":28735469},"geometry":{"x":-8270551.931143562,"y":4960000.000000002}},{"attributes":{"count":1,"NRRrcNewCellIndEvt":"1","OBJECTID":1463107501},"geometry":{"x":-8268819.880335992,"y":4962999.999999999}},{"attributes":{"count":1,"NRRrcNewCellIndEvt":"1","OBJECTID":1828287594},"geometry":{"x":-8260159.626298148,"y":4983999.999999998}},{"attributes":{"count":1,"NRRrcNewCellIndEvt":"1","OBJECTID":653868354},"geometry":{"x":-8254963.473875443,"y":4986999.999999998}}],"exceededTransferLimit":false,"geometryType":"esriGeometryPoint"}
